infi.nose_plugins-0.0.9-py2.7-nspkg.pth
infi/nose_plugins/__init__.py
infi/nose_plugins/__version__.py
infi/nose_plugins/logbook.py
infi/nose_plugins/requestswarnings.py
infi/nose_plugins/stderr.py
infi/nose_plugins/html/__init__.py
infi/nose_plugins/html/__init__backup.py
infi/nose_plugins/html/ajax.py
infi.nose_plugins-0.0.9.dist-info/LICENSE
infi.nose_plugins-0.0.9.dist-info/METADATA
infi.nose_plugins-0.0.9.dist-info/WHEEL
infi.nose_plugins-0.0.9.dist-info/entry_points.txt
infi.nose_plugins-0.0.9.dist-info/namespace_packages.txt
infi.nose_plugins-0.0.9.dist-info/top_level.txt
infi.nose_plugins-0.0.9.dist-info/RECORD
