Metadata-Version: 2.1
Name: infi.nose-plugins
Version: 0.0.9
Summary: nose plugins
Home-page: https://git.infinidat.com/host-opensource/infi.nose_plugins
Author: Arnon Yaari
Author-email: arnony@infinidat.com
License: BSD
Platform: UNKNOWN
Classifier: Intended Audience :: Developers
Classifier: Intended Audience :: System Administrators
Classifier: License :: OSI Approved :: BSD License
Classifier: Operating System :: OS Independent
Classifier: Programming Language :: Python
Classifier: Topic :: Software Development :: Libraries :: Python Modules
Requires-Dist: nose
Requires-Dist: setuptools
Requires-Dist: requests
